dtviz/decoder.py
dtviz/encoder.py
dtviz/common.py
dtviz/__main__.py
dtviz/main.py
dtviz/args.py
dtviz/__init__.py
dtviz-0.2.2.dist-info/LICENSE
dtviz-0.2.2.dist-info/entry_points.txt
dtviz-0.2.2.dist-info/METADATA
dtviz-0.2.2.dist-info/WHEEL
dtviz-0.2.2.dist-info/RECORD
