Metadata-Version: 2.1
Name: dtviz
Version: 0.2.2
Summary: Dependency tree visualizer
License: GPLv3
Classifier: Programming Language :: Python :: 3
Classifier: License :: OSI Approved :: GNU General Public License v3 (GPLv3)
Provides-Extra: dev
Requires-Dist: hat-json ~=0.6.3
Requires-Dist: packaging ~=25.0
Requires-Dist: mkwhl ~=0.3.1; extra == 'dev'
Requires-Python: >=3.10
Project-URL: Repository, https://github.com/bozokopic/dtviz.git
